pyrtable/__init__.py
pyrtable/_baseandtable.py
pyrtable/configutils.py
pyrtable/connectionmanager.py
pyrtable/context/__init__.py
pyrtable/context/base.py
pyrtable/exceptions.py
pyrtable/fields/__init__.py
pyrtable/fields/attachment.py
pyrtable/fields/base.py
pyrtable/fields/basic.py
pyrtable/fields/recordlink.py
pyrtable/fields/selection.py
pyrtable/fields/valueset.py
pyrtable/filters/__init__.py
pyrtable/filters/base.py
pyrtable/filters/q.py
pyrtable/filters/raw.py
pyrtable/filterutils.py
pyrtable/query.py
pyrtable/record.py
pyrtable-0.10.2.dist-info/LICENSE
pyrtable-0.10.2.dist-info/WHEEL
pyrtable-0.10.2.dist-info/METADATA
pyrtable-0.10.2.dist-info/RECORD
