Metadata-Version: 2.1
Name: pyrtable
Version: 0.10.2
Summary: Django-inspired library to interface with Airtable
Home-page: https://github.com/vilarneto/pyrtable
License: MIT
Author: Vilar da Camara Neto
Author-email: vilarneto@gmail.com
Requires-Python: >=3.8,<4.0
Classifier: Development Status :: 4 - Beta
Classifier: Environment :: Console
Classifier: Intended Audience :: Developers
Classifier: License :: OSI Approved :: MIT License
Classifier: Natural Language :: English
Classifier: Operating System :: OS Independent
Classifier: Programming Language :: Python
Classifier: Programming Language :: Python :: 3
Classifier: Programming Language :: Python :: 3.8
Classifier: Programming Language :: Python :: 3.9
Classifier: Programming Language :: Python :: 3.10
Classifier: Programming Language :: Python :: 3.11
Classifier: Programming Language :: Python :: 3.10
Classifier: Programming Language :: Python :: 3.8
Classifier: Programming Language :: Python :: 3.9
Classifier: Programming Language :: Python :: Implementation :: CPython
Classifier: Topic :: Software Development
Requires-Dist: deprecated
Requires-Dist: pyyaml (>=5.1,<7)
Requires-Dist: requests (>=2.22.0,<3.0.0)
Requires-Dist: simplejson (>=3.16.0,<4.0.0)
Project-URL: Documentation, https://pyrtable.readthedocs.io/
Project-URL: Repository, https://github.com/vilarneto/pyrtable
